[
  {
    "pincode": "175138",
    "officename": "Babeli S.O",
    "officeType": "S.O",
    "Deliverystatus": "Delivery",
    "divisionname": "Mandi",
    "regionname": "Shimla HQ",
    "circlename": "Himachal Pradesh",
    "Taluk": "Kullu(T)",
    "Districtname": "Kullu",
    "statename": "HIMACHAL PRADESH"
  },
  {
    "pincode": "175138",
    "officename": "Neoli B.O",
    "officeType": "B.O",
    "Deliverystatus": "Delivery",
    "divisionname": "Mandi",
    "regionname": "Shimla HQ",
    "circlename": "Himachal Pradesh",
    "Taluk": "Kullu(T)",
    "Districtname": "Kullu",
    "statename": "HIMACHAL PRADESH"
  },
  {
    "pincode": "175138",
    "officename": "Seobag B.O",
    "officeType": "B.O",
    "Deliverystatus": "Delivery",
    "divisionname": "Mandi",
    "regionname": "Shimla HQ",
    "circlename": "Himachal Pradesh",
    "Taluk": "Kullu(T)",
    "Districtname": "Kullu",
    "statename": "HIMACHAL PRADESH"
  }
]
