[
  {
    "pincode": "206246",
    "officename": "Belhupur B.O",
    "officeType": "B.O",
    "Deliverystatus": "Delivery",
    "divisionname": "Etawah",
    "regionname": "Agra",
    "circlename": "Uttar Pradesh",
    "Taluk": "Auraiya",
    "Districtname": "Auraiya",
    "statename": "UTTAR PRADESH"
  },
  {
    "pincode": "206246",
    "officename": "Binpurapur B.O",
    "officeType": "B.O",
    "Deliverystatus": "Delivery",
    "divisionname": "Etawah",
    "regionname": "Agra",
    "circlename": "Uttar Pradesh",
    "Taluk": "Auraiya",
    "Districtname": "Auraiya",
    "statename": "UTTAR PRADESH"
  },
  {
    "pincode": "206246",
    "officename": "Dahgaon B.O",
    "officeType": "B.O",
    "Deliverystatus": "Delivery",
    "divisionname": "Etawah",
    "regionname": "Agra",
    "circlename": "Uttar Pradesh",
    "Taluk": "Auraiya",
    "Districtname": "Auraiya",
    "statename": "UTTAR PRADESH"
  },
  {
    "pincode": "206246",
    "officename": "Kanchausi Bazar S.O",
    "officeType": "S.O",
    "Deliverystatus": "Delivery",
    "divisionname": "Etawah",
    "regionname": "Agra",
    "circlename": "Uttar Pradesh",
    "Taluk": "Auraiya",
    "Districtname": "Auraiya",
    "statename": "UTTAR PRADESH"
  },
  {
    "pincode": "206246",
    "officename": "Kanhausi B.O",
    "officeType": "B.O",
    "Deliverystatus": "Delivery",
    "divisionname": "Etawah",
    "regionname": "Agra",
    "circlename": "Uttar Pradesh",
    "Taluk": "Auraiya",
    "Districtname": "Auraiya",
    "statename": "UTTAR PRADESH"
  },
  {
    "pincode": "206246",
    "officename": "Lahrapur B.O",
    "officeType": "B.O",
    "Deliverystatus": "Delivery",
    "divisionname": "Etawah",
    "regionname": "Agra",
    "circlename": "Uttar Pradesh",
    "Taluk": "Auraiya",
    "Districtname": "Auraiya",
    "statename": "UTTAR PRADESH"
  },
  {
    "pincode": "206246",
    "officename": "Madhwapur B.O",
    "officeType": "B.O",
    "Deliverystatus": "Delivery",
    "divisionname": "Etawah",
    "regionname": "Agra",
    "circlename": "Uttar Pradesh",
    "Taluk": "Auraiya",
    "Districtname": "Auraiya",
    "statename": "UTTAR PRADESH"
  },
  {
    "pincode": "206246",
    "officename": "Navgawan B.O",
    "officeType": "B.O",
    "Deliverystatus": "Delivery",
    "divisionname": "Etawah",
    "regionname": "Agra",
    "circlename": "Uttar Pradesh",
    "Taluk": "Auraiya",
    "Districtname": "Auraiya",
    "statename": "UTTAR PRADESH"
  }
]
