[
  {
    "pincode": "273403",
    "officename": "Baghrain B.O",
    "officeType": "B.O",
    "Deliverystatus": "Delivery",
    "divisionname": "Gorakhpur",
    "regionname": "Gorakhpur",
    "circlename": "Uttar Pradesh",
    "Taluk": "Basgaon",
    "Districtname": "Gorakhpur",
    "statename": "UTTAR PRADESH"
  },
  {
    "pincode": "273403",
    "officename": "Bansgaon S.O (Gorakhpur)",
    "officeType": "S.O",
    "Deliverystatus": "Delivery",
    "divisionname": "Gorakhpur",
    "regionname": "Gorakhpur",
    "circlename": "Uttar Pradesh",
    "Taluk": "Bansgaon",
    "Districtname": "Gorakhpur",
    "statename": "UTTAR PRADESH"
  },
  {
    "pincode": "273403",
    "officename": "Bhita B.O",
    "officeType": "B.O",
    "Deliverystatus": "Delivery",
    "divisionname": "Gorakhpur",
    "regionname": "Gorakhpur",
    "circlename": "Uttar Pradesh",
    "Taluk": "Bansgaon",
    "Districtname": "Gorakhpur",
    "statename": "UTTAR PRADESH"
  },
  {
    "pincode": "273403",
    "officename": "Bhuswal B.O",
    "officeType": "B.O",
    "Deliverystatus": "Delivery",
    "divisionname": "Gorakhpur",
    "regionname": "Gorakhpur",
    "circlename": "Uttar Pradesh",
    "Taluk": "Bansgaon",
    "Districtname": "Gorakhpur",
    "statename": "UTTAR PRADESH"
  },
  {
    "pincode": "273403",
    "officename": "Bisaunpur B.O",
    "officeType": "B.O",
    "Deliverystatus": "Delivery",
    "divisionname": "Gorakhpur",
    "regionname": "Gorakhpur",
    "circlename": "Uttar Pradesh",
    "Taluk": "Bansgaon",
    "Districtname": "Gorakhpur",
    "statename": "UTTAR PRADESH"
  },
  {
    "pincode": "273403",
    "officename": "Hata Buzurg B.O",
    "officeType": "B.O",
    "Deliverystatus": "Delivery",
    "divisionname": "Gorakhpur",
    "regionname": "Gorakhpur",
    "circlename": "Uttar Pradesh",
    "Taluk": "Basgaon",
    "Districtname": "Gorakhpur",
    "statename": "UTTAR PRADESH"
  },
  {
    "pincode": "273403",
    "officename": "Jigina Bhion B.O",
    "officeType": "B.O",
    "Deliverystatus": "Delivery",
    "divisionname": "Gorakhpur",
    "regionname": "Gorakhpur",
    "circlename": "Uttar Pradesh",
    "Taluk": "Basgaon",
    "Districtname": "Gorakhpur",
    "statename": "UTTAR PRADESH"
  },
  {
    "pincode": "273403",
    "officename": "Kanapar B.O",
    "officeType": "B.O",
    "Deliverystatus": "Delivery",
    "divisionname": "Gorakhpur",
    "regionname": "Gorakhpur",
    "circlename": "Uttar Pradesh",
    "Taluk": "Bansgaon",
    "Districtname": "Gorakhpur",
    "statename": "UTTAR PRADESH"
  },
  {
    "pincode": "273403",
    "officename": "Malahanpar B.O",
    "officeType": "B.O",
    "Deliverystatus": "Delivery",
    "divisionname": "Gorakhpur",
    "regionname": "Gorakhpur",
    "circlename": "Uttar Pradesh",
    "Taluk": "Bansgaon",
    "Districtname": "Gorakhpur",
    "statename": "UTTAR PRADESH"
  },
  {
    "pincode": "273403",
    "officename": "Pali B.O",
    "officeType": "B.O",
    "Deliverystatus": "Delivery",
    "divisionname": "Gorakhpur",
    "regionname": "Gorakhpur",
    "circlename": "Uttar Pradesh",
    "Taluk": "Bansgaon",
    "Districtname": "Gorakhpur",
    "statename": "UTTAR PRADESH"
  },
  {
    "pincode": "273403",
    "officename": "Pandeypura B.O",
    "officeType": "B.O",
    "Deliverystatus": "Delivery",
    "divisionname": "Gorakhpur",
    "regionname": "Gorakhpur",
    "circlename": "Uttar Pradesh",
    "Taluk": "",
    "Districtname": "Gorakhpur",
    "statename": "UTTAR PRADESH"
  },
  {
    "pincode": "273403",
    "officename": "Sahupar B.O",
    "officeType": "B.O",
    "Deliverystatus": "Delivery",
    "divisionname": "Gorakhpur",
    "regionname": "Gorakhpur",
    "circlename": "Uttar Pradesh",
    "Taluk": "",
    "Districtname": "Gorakhpur",
    "statename": "UTTAR PRADESH"
  },
  {
    "pincode": "273403",
    "officename": "Siswa Urf Siuwa B.O",
    "officeType": "B.O",
    "Deliverystatus": "Delivery",
    "divisionname": "Gorakhpur",
    "regionname": "Gorakhpur",
    "circlename": "Uttar Pradesh",
    "Taluk": "Bansgaon",
    "Districtname": "Gorakhpur",
    "statename": "UTTAR PRADESH"
  }
]
