[
  {
    "pincode": "274407",
    "officename": "Bagahi B.O",
    "officeType": "B.O",
    "Deliverystatus": "Delivery",
    "divisionname": "Deoria",
    "regionname": "Gorakhpur",
    "circlename": "Uttar Pradesh",
    "Taluk": "",
    "Districtname": "Kushinagar",
    "statename": "UTTAR PRADESH"
  },
  {
    "pincode": "274407",
    "officename": "Barwa Raja Pakar B.O",
    "officeType": "B.O",
    "Deliverystatus": "Delivery",
    "divisionname": "Deoria",
    "regionname": "Gorakhpur",
    "circlename": "Uttar Pradesh",
    "Taluk": "",
    "Districtname": "Kushinagar",
    "statename": "UTTAR PRADESH"
  },
  {
    "pincode": "274407",
    "officename": "Dhuria Imilia B.O",
    "officeType": "B.O",
    "Deliverystatus": "Delivery",
    "divisionname": "Deoria",
    "regionname": "Gorakhpur",
    "circlename": "Uttar Pradesh",
    "Taluk": "",
    "Districtname": "Kushinagar",
    "statename": "UTTAR PRADESH"
  },
  {
    "pincode": "274407",
    "officename": "Laxmipur Baboo B.O",
    "officeType": "B.O",
    "Deliverystatus": "Delivery",
    "divisionname": "Deoria",
    "regionname": "Gorakhpur",
    "circlename": "Uttar Pradesh",
    "Taluk": "Tamkuhi",
    "Districtname": "Kushinagar",
    "statename": "UTTAR PRADESH"
  },
  {
    "pincode": "274407",
    "officename": "Pagara Prsad Giri B.O",
    "officeType": "B.O",
    "Deliverystatus": "Delivery",
    "divisionname": "Deoria",
    "regionname": "Gorakhpur",
    "circlename": "Uttar Pradesh",
    "Taluk": "",
    "Districtname": "Kushinagar",
    "statename": "UTTAR PRADESH"
  },
  {
    "pincode": "274407",
    "officename": "Parsauni Buzurg B.O",
    "officeType": "B.O",
    "Deliverystatus": "Delivery",
    "divisionname": "Deoria",
    "regionname": "Gorakhpur",
    "circlename": "Uttar Pradesh",
    "Taluk": "",
    "Districtname": "Kushinagar",
    "statename": "UTTAR PRADESH"
  },
  {
    "pincode": "274407",
    "officename": "Tamkuhi S.O",
    "officeType": "S.O",
    "Deliverystatus": "Delivery",
    "divisionname": "Deoria",
    "regionname": "Gorakhpur",
    "circlename": "Uttar Pradesh",
    "Taluk": "",
    "Districtname": "Kushinagar",
    "statename": "UTTAR PRADESH"
  }
]
