[
  {
    "pincode": "282005",
    "officename": "Dayal Bagh S.O",
    "officeType": "S.O",
    "Deliverystatus": "Delivery",
    "divisionname": "Agra",
    "regionname": "Agra",
    "circlename": "Uttar Pradesh",
    "Taluk": "",
    "Districtname": "Agra",
    "statename": "UTTAR PRADESH"
  },
  {
    "pincode": "282005",
    "officename": "Jaganpur B.O",
    "officeType": "B.O",
    "Deliverystatus": "Delivery",
    "divisionname": "Agra",
    "regionname": "Agra",
    "circlename": "Uttar Pradesh",
    "Taluk": "",
    "Districtname": "Agra",
    "statename": "UTTAR PRADESH"
  },
  {
    "pincode": "282005",
    "officename": "K.H.Sansthan S.O",
    "officeType": "S.O",
    "Deliverystatus": "Non-Delivery",
    "divisionname": "Agra",
    "regionname": "Agra",
    "circlename": "Uttar Pradesh",
    "Taluk": "",
    "Districtname": "Agra",
    "statename": "UTTAR PRADESH"
  },
  {
    "pincode": "282005",
    "officename": "Karmyogi Enclave S.O",
    "officeType": "S.O",
    "Deliverystatus": "Non-Delivery",
    "divisionname": "Agra",
    "regionname": "Agra",
    "circlename": "Uttar Pradesh",
    "Taluk": "Agra",
    "Districtname": "Agra",
    "statename": "UTTAR PRADESH"
  },
  {
    "pincode": "282005",
    "officename": "New Agra S.O",
    "officeType": "S.O",
    "Deliverystatus": "Non-Delivery",
    "divisionname": "Agra",
    "regionname": "Agra",
    "circlename": "Uttar Pradesh",
    "Taluk": "",
    "Districtname": "Agra",
    "statename": "UTTAR PRADESH"
  }
]
