[
  {
    "pincode": "327026",
    "officename": "Badgun B.O",
    "officeType": "B.O",
    "Deliverystatus": "Delivery",
    "divisionname": "Dungarpur",
    "regionname": "Ajmer",
    "circlename": "Rajasthan",
    "Taluk": "Banswara",
    "Districtname": "Banswara",
    "statename": "RAJASTHAN"
  },
  {
    "pincode": "327026",
    "officename": "Bhungda B.O",
    "officeType": "B.O",
    "Deliverystatus": "Delivery",
    "divisionname": "Dungarpur",
    "regionname": "Ajmer",
    "circlename": "Rajasthan",
    "Taluk": "Banswara",
    "Districtname": "Banswara",
    "statename": "RAJASTHAN"
  },
  {
    "pincode": "327026",
    "officename": "Bori B.O",
    "officeType": "B.O",
    "Deliverystatus": "Delivery",
    "divisionname": "Dungarpur",
    "regionname": "Ajmer",
    "circlename": "Rajasthan",
    "Taluk": "Banswara",
    "Districtname": "Banswara",
    "statename": "RAJASTHAN"
  },
  {
    "pincode": "327026",
    "officename": "Cheev B.O",
    "officeType": "B.O",
    "Deliverystatus": "Delivery",
    "divisionname": "Dungarpur",
    "regionname": "Ajmer",
    "circlename": "Rajasthan",
    "Taluk": "Banswara",
    "Districtname": "Banswara",
    "statename": "RAJASTHAN"
  },
  {
    "pincode": "327026",
    "officename": "Kelamela B.O",
    "officeType": "B.O",
    "Deliverystatus": "Delivery",
    "divisionname": "Dungarpur",
    "regionname": "Ajmer",
    "circlename": "Rajasthan",
    "Taluk": "Banswara",
    "Districtname": "Banswara",
    "statename": "RAJASTHAN"
  },
  {
    "pincode": "327026",
    "officename": "Kherdabada B.O",
    "officeType": "B.O",
    "Deliverystatus": "Delivery",
    "divisionname": "Dungarpur",
    "regionname": "Ajmer",
    "circlename": "Rajasthan",
    "Taluk": "Banswara",
    "Districtname": "Banswara",
    "statename": "RAJASTHAN"
  },
  {
    "pincode": "327026",
    "officename": "Kupda B.O",
    "officeType": "B.O",
    "Deliverystatus": "Delivery",
    "divisionname": "Dungarpur",
    "regionname": "Ajmer",
    "circlename": "Rajasthan",
    "Taluk": "Banswara",
    "Districtname": "Banswara",
    "statename": "RAJASTHAN"
  },
  {
    "pincode": "327026",
    "officename": "Mahidam S.O",
    "officeType": "S.O",
    "Deliverystatus": "Delivery",
    "divisionname": "Dungarpur",
    "regionname": "Ajmer",
    "circlename": "Rajasthan",
    "Taluk": "Banswara",
    "Districtname": "Banswara",
    "statename": "RAJASTHAN"
  }
]
