[
  {
    "pincode": "363320",
    "officename": "Bharad B.O",
    "officeType": "B.O",
    "Deliverystatus": "Delivery",
    "divisionname": "Surendranagar",
    "regionname": "Rajkot",
    "circlename": "Gujarat",
    "Taluk": "Dhrangadhra",
    "Districtname": "Surendra Nagar",
    "statename": "GUJARAT"
  },
  {
    "pincode": "363320",
    "officename": "Devcharadi B.O",
    "officeType": "B.O",
    "Deliverystatus": "Delivery",
    "divisionname": "Surendranagar",
    "regionname": "Rajkot",
    "circlename": "Gujarat",
    "Taluk": "Dhrangadhra",
    "Districtname": "Surendra Nagar",
    "statename": "GUJARAT"
  },
  {
    "pincode": "363320",
    "officename": "Dholi B.O",
    "officeType": "B.O",
    "Deliverystatus": "Delivery",
    "divisionname": "Surendranagar",
    "regionname": "Rajkot",
    "circlename": "Gujarat",
    "Taluk": "Dhrangadhra",
    "Districtname": "Surendra Nagar",
    "statename": "GUJARAT"
  },
  {
    "pincode": "363320",
    "officename": "Dumana B.O",
    "officeType": "B.O",
    "Deliverystatus": "Delivery",
    "divisionname": "Surendranagar",
    "regionname": "Rajkot",
    "circlename": "Gujarat",
    "Taluk": "Dhrangadhra",
    "Districtname": "Surendra Nagar",
    "statename": "GUJARAT"
  },
  {
    "pincode": "363320",
    "officename": "Ganjela B.O",
    "officeType": "B.O",
    "Deliverystatus": "Delivery",
    "divisionname": "Surendranagar",
    "regionname": "Rajkot",
    "circlename": "Gujarat",
    "Taluk": "Dhrangadhra",
    "Districtname": "Surendra Nagar",
    "statename": "GUJARAT"
  },
  {
    "pincode": "363320",
    "officename": "Hampar B.O",
    "officeType": "B.O",
    "Deliverystatus": "Delivery",
    "divisionname": "Surendranagar",
    "regionname": "Rajkot",
    "circlename": "Gujarat",
    "Taluk": "Dhrangadhra",
    "Districtname": "Surendra Nagar",
    "statename": "GUJARAT"
  },
  {
    "pincode": "363320",
    "officename": "Khambhada B.O",
    "officeType": "B.O",
    "Deliverystatus": "Delivery",
    "divisionname": "Surendranagar",
    "regionname": "Rajkot",
    "circlename": "Gujarat",
    "Taluk": "Dhrangadhra",
    "Districtname": "Surendra Nagar",
    "statename": "GUJARAT"
  },
  {
    "pincode": "363320",
    "officename": "Navalgadh B.O",
    "officeType": "B.O",
    "Deliverystatus": "Delivery",
    "divisionname": "Surendranagar",
    "regionname": "Rajkot",
    "circlename": "Gujarat",
    "Taluk": "Dhrangadhra",
    "Districtname": "Surendra Nagar",
    "statename": "GUJARAT"
  },
  {
    "pincode": "363320",
    "officename": "Pratappur B.O",
    "officeType": "B.O",
    "Deliverystatus": "Delivery",
    "divisionname": "Surendranagar",
    "regionname": "Rajkot",
    "circlename": "Gujarat",
    "Taluk": "Dhrangadhra",
    "Districtname": "Surendra Nagar",
    "statename": "GUJARAT"
  },
  {
    "pincode": "363320",
    "officename": "Rajcharadi B.O",
    "officeType": "B.O",
    "Deliverystatus": "Delivery",
    "divisionname": "Surendranagar",
    "regionname": "Rajkot",
    "circlename": "Gujarat",
    "Taluk": "Dhrangadhra",
    "Districtname": "Surendra Nagar",
    "statename": "GUJARAT"
  },
  {
    "pincode": "363320",
    "officename": "Rajsitapur S.O",
    "officeType": "S.O",
    "Deliverystatus": "Delivery",
    "divisionname": "Surendranagar",
    "regionname": "Rajkot",
    "circlename": "Gujarat",
    "Taluk": "Dhrangadhra",
    "Districtname": "Surendra Nagar",
    "statename": "GUJARAT"
  }
]
