[
  {
    "pincode": "382145",
    "officename": "Balsasan B.O",
    "officeType": "B.O",
    "Deliverystatus": "Delivery",
    "divisionname": "Gandhinagar",
    "regionname": "Ahmedabad HQ",
    "circlename": "Gujarat",
    "Taluk": "Detroj-rampura",
    "Districtname": "Ahmedabad",
    "statename": "GUJARAT"
  },
  {
    "pincode": "382145",
    "officename": "Bamroli B.O",
    "officeType": "B.O",
    "Deliverystatus": "Delivery",
    "divisionname": "Gandhinagar",
    "regionname": "Ahmedabad HQ",
    "circlename": "Gujarat",
    "Taluk": "Detrioj-rampura",
    "Districtname": "Ahmedabad",
    "statename": "GUJARAT"
  },
  {
    "pincode": "382145",
    "officename": "Bhoyani B.O",
    "officeType": "B.O",
    "Deliverystatus": "Delivery",
    "divisionname": "Gandhinagar",
    "regionname": "Ahmedabad HQ",
    "circlename": "Gujarat",
    "Taluk": "Detroj-rampura",
    "Districtname": "Ahmedabad",
    "statename": "GUJARAT"
  },
  {
    "pincode": "382145",
    "officename": "Chuval Dangarva B.O",
    "officeType": "B.O",
    "Deliverystatus": "Delivery",
    "divisionname": "Gandhinagar",
    "regionname": "Ahmedabad HQ",
    "circlename": "Gujarat",
    "Taluk": "Detroj Rampura",
    "Districtname": "Ahmedabad",
    "statename": "GUJARAT"
  },
  {
    "pincode": "382145",
    "officename": "Katosan Road S.O",
    "officeType": "S.O",
    "Deliverystatus": "Delivery",
    "divisionname": "Gandhinagar",
    "regionname": "Ahmedabad HQ",
    "circlename": "Gujarat",
    "Taluk": "Detroj-Rampura",
    "Districtname": "Ahmedabad",
    "statename": "GUJARAT"
  },
  {
    "pincode": "382145",
    "officename": "Madrisana B.O",
    "officeType": "B.O",
    "Deliverystatus": "Delivery",
    "divisionname": "Gandhinagar",
    "regionname": "Ahmedabad HQ",
    "circlename": "Gujarat",
    "Taluk": "Detroj-rampura",
    "Districtname": "Ahmedabad",
    "statename": "GUJARAT"
  },
  {
    "pincode": "382145",
    "officename": "Moti Rantai B.O",
    "officeType": "B.O",
    "Deliverystatus": "Delivery",
    "divisionname": "Gandhinagar",
    "regionname": "Ahmedabad HQ",
    "circlename": "Gujarat",
    "Taluk": "Detroj-rampura",
    "Districtname": "Ahmedabad",
    "statename": "GUJARAT"
  },
  {
    "pincode": "382145",
    "officename": "Sobhasan B.O",
    "officeType": "B.O",
    "Deliverystatus": "Delivery",
    "divisionname": "Gandhinagar",
    "regionname": "Ahmedabad HQ",
    "circlename": "Gujarat",
    "Taluk": "Detroj-rampura",
    "Districtname": "Ahmedabad",
    "statename": "GUJARAT"
  },
  {
    "pincode": "382145",
    "officename": "Sunvala B.O",
    "officeType": "B.O",
    "Deliverystatus": "Delivery",
    "divisionname": "Gandhinagar",
    "regionname": "Ahmedabad HQ",
    "circlename": "Gujarat",
    "Taluk": "Detroj-rampura",
    "Districtname": "Ahmedabad",
    "statename": "GUJARAT"
  },
  {
    "pincode": "382145",
    "officename": "Telavi B.O",
    "officeType": "B.O",
    "Deliverystatus": "Delivery",
    "divisionname": "Gandhinagar",
    "regionname": "Ahmedabad HQ",
    "circlename": "Gujarat",
    "Taluk": "Detroj-rampura",
    "Districtname": "Ahmedabad",
    "statename": "GUJARAT"
  }
]
