[
  {
    "pincode": "396530",
    "officename": "Chasa B.O",
    "officeType": "B.O",
    "Deliverystatus": "Delivery",
    "divisionname": "Navsari",
    "regionname": "Vadodara",
    "circlename": "Gujarat",
    "Taluk": "Chikhli",
    "Districtname": "Navsari",
    "statename": "GUJARAT"
  },
  {
    "pincode": "396530",
    "officename": "Degam S.O",
    "officeType": "S.O",
    "Deliverystatus": "Delivery",
    "divisionname": "Navsari",
    "regionname": "Vadodara",
    "circlename": "Gujarat",
    "Taluk": "Chikhli",
    "Districtname": "Navsari",
    "statename": "GUJARAT"
  },
  {
    "pincode": "396530",
    "officename": "Suthvad B.O",
    "officeType": "B.O",
    "Deliverystatus": "Delivery",
    "divisionname": "Navsari",
    "regionname": "Vadodara",
    "circlename": "Gujarat",
    "Taluk": "Chikhli",
    "Districtname": "Navsari",
    "statename": "GUJARAT"
  }
]
