[
  {
    "pincode": "400032",
    "officename": "High Court Building S.O (Mumbai)",
    "officeType": "S.O",
    "Deliverystatus": "Non-Delivery",
    "divisionname": "Mumbai  South",
    "regionname": "Mumbai",
    "circlename": "Maharashtra",
    "Taluk": "Mumbai",
    "Districtname": "Mumbai",
    "statename": "MAHARASHTRA"
  },
  {
    "pincode": "400032",
    "officename": "Mantralaya S.O (Mumbai)",
    "officeType": "S.O",
    "Deliverystatus": "Delivery",
    "divisionname": "Mumbai  South",
    "regionname": "Mumbai",
    "circlename": "Maharashtra",
    "Taluk": "Mumbai",
    "Districtname": "Mumbai",
    "statename": "MAHARASHTRA"
  },
  {
    "pincode": "400032",
    "officename": "Secretariate S.O",
    "officeType": "S.O",
    "Deliverystatus": "Non-Delivery",
    "divisionname": "Mumbai  South",
    "regionname": "Mumbai",
    "circlename": "Maharashtra",
    "Taluk": "Mumbai",
    "Districtname": "Mumbai",
    "statename": "MAHARASHTRA"
  }
]
