[
  {
    "pincode": "413534",
    "officename": "Ghatpimpri B.O",
    "officeType": "B.O",
    "Deliverystatus": "Delivery",
    "divisionname": "Osmanabad",
    "regionname": "Aurangabad",
    "circlename": "Maharashtra",
    "Taluk": "Bhoom",
    "Districtname": "Osmanabad",
    "statename": "MAHARASHTRA"
  },
  {
    "pincode": "413534",
    "officename": "Ieet S.O",
    "officeType": "S.O",
    "Deliverystatus": "Delivery",
    "divisionname": "Osmanabad",
    "regionname": "Aurangabad",
    "circlename": "Maharashtra",
    "Taluk": "Bhoom",
    "Districtname": "Osmanabad",
    "statename": "MAHARASHTRA"
  },
  {
    "pincode": "413534",
    "officename": "Lanjeshwar B.O",
    "officeType": "B.O",
    "Deliverystatus": "Delivery",
    "divisionname": "Osmanabad",
    "regionname": "Aurangabad",
    "circlename": "Maharashtra",
    "Taluk": "Bhoom",
    "Districtname": "Osmanabad",
    "statename": "MAHARASHTRA"
  },
  {
    "pincode": "413534",
    "officename": "Nipani B.O",
    "officeType": "B.O",
    "Deliverystatus": "Delivery",
    "divisionname": "Osmanabad",
    "regionname": "Aurangabad",
    "circlename": "Maharashtra",
    "Taluk": "Bhoom",
    "Districtname": "Osmanabad",
    "statename": "MAHARASHTRA"
  },
  {
    "pincode": "413534",
    "officename": "Pakhrud B.O",
    "officeType": "B.O",
    "Deliverystatus": "Delivery",
    "divisionname": "Osmanabad",
    "regionname": "Aurangabad",
    "circlename": "Maharashtra",
    "Taluk": "Bhoom",
    "Districtname": "Osmanabad",
    "statename": "MAHARASHTRA"
  }
]
