[
  {
    "pincode": "415803",
    "officename": "Anjanari B.O",
    "officeType": "B.O",
    "Deliverystatus": "Delivery",
    "divisionname": "Ratnagiri",
    "regionname": "Goa-Panaji",
    "circlename": "Maharashtra",
    "Taluk": "Lanja",
    "Districtname": "Ratnagiri",
    "statename": "MAHARASHTRA"
  },
  {
    "pincode": "415803",
    "officename": "Choravane B.O",
    "officeType": "B.O",
    "Deliverystatus": "Delivery",
    "divisionname": "Ratnagiri",
    "regionname": "Goa-Panaji",
    "circlename": "Maharashtra",
    "Taluk": "Sangmeshwar",
    "Districtname": "Ratnagiri",
    "statename": "MAHARASHTRA"
  },
  {
    "pincode": "415803",
    "officename": "Dabhole B.O",
    "officeType": "B.O",
    "Deliverystatus": "Delivery",
    "divisionname": "Ratnagiri",
    "regionname": "Goa-Panaji",
    "circlename": "Maharashtra",
    "Taluk": "Chiplun",
    "Districtname": "Ratnagiri",
    "statename": "MAHARASHTRA"
  },
  {
    "pincode": "415803",
    "officename": "Ghativale B.O",
    "officeType": "B.O",
    "Deliverystatus": "Delivery",
    "divisionname": "Ratnagiri",
    "regionname": "Goa-Panaji",
    "circlename": "Maharashtra",
    "Taluk": "Sangmeshwar",
    "Districtname": "Ratnagiri",
    "statename": "MAHARASHTRA"
  },
  {
    "pincode": "415803",
    "officename": "Kankadi B.O",
    "officeType": "B.O",
    "Deliverystatus": "Delivery",
    "divisionname": "Ratnagiri",
    "regionname": "Goa-Panaji",
    "circlename": "Maharashtra",
    "Taluk": "Sangmeshwar",
    "Districtname": "Ratnagiri",
    "statename": "MAHARASHTRA"
  },
  {
    "pincode": "415803",
    "officename": "Khanu B.O",
    "officeType": "B.O",
    "Deliverystatus": "Delivery",
    "divisionname": "Ratnagiri",
    "regionname": "Goa-Panaji",
    "circlename": "Maharashtra",
    "Taluk": "Ratnagiri",
    "Districtname": "Ratnagiri",
    "statename": "MAHARASHTRA"
  },
  {
    "pincode": "415803",
    "officename": "Math B.O",
    "officeType": "B.O",
    "Deliverystatus": "Delivery",
    "divisionname": "Ratnagiri",
    "regionname": "Goa-Panaji",
    "circlename": "Maharashtra",
    "Taluk": "Lanja",
    "Districtname": "Ratnagiri",
    "statename": "MAHARASHTRA"
  },
  {
    "pincode": "415803",
    "officename": "Nanij B.O",
    "officeType": "B.O",
    "Deliverystatus": "Delivery",
    "divisionname": "Ratnagiri",
    "regionname": "Goa-Panaji",
    "circlename": "Maharashtra",
    "Taluk": "Ratnagiri",
    "Districtname": "Ratnagiri",
    "statename": "MAHARASHTRA"
  },
  {
    "pincode": "415803",
    "officename": "Nivsar B.O",
    "officeType": "B.O",
    "Deliverystatus": "Delivery",
    "divisionname": "Ratnagiri",
    "regionname": "Goa-Panaji",
    "circlename": "Maharashtra",
    "Taluk": "Lanja",
    "Districtname": "Ratnagiri",
    "statename": "MAHARASHTRA"
  },
  {
    "pincode": "415803",
    "officename": "Pali (RTG) S.O",
    "officeType": "S.O",
    "Deliverystatus": "Delivery",
    "divisionname": "Ratnagiri",
    "regionname": "Goa-Panaji",
    "circlename": "Maharashtra",
    "Taluk": "Ratnagiri",
    "Districtname": "Ratnagiri",
    "statename": "MAHARASHTRA"
  },
  {
    "pincode": "415803",
    "officename": "Sathare Bambar B.O",
    "officeType": "B.O",
    "Deliverystatus": "Delivery",
    "divisionname": "Ratnagiri",
    "regionname": "Goa-Panaji",
    "circlename": "Maharashtra",
    "Taluk": "Ratnagiri",
    "Districtname": "Ratnagiri",
    "statename": "MAHARASHTRA"
  },
  {
    "pincode": "415803",
    "officename": "Shirambavali B.O",
    "officeType": "B.O",
    "Deliverystatus": "Delivery",
    "divisionname": "Ratnagiri",
    "regionname": "Goa-Panaji",
    "circlename": "Maharashtra",
    "Taluk": "Lanja",
    "Districtname": "Ratnagiri",
    "statename": "MAHARASHTRA"
  },
  {
    "pincode": "415803",
    "officename": "Wanke B.O",
    "officeType": "B.O",
    "Deliverystatus": "Delivery",
    "divisionname": "Ratnagiri",
    "regionname": "Goa-Panaji",
    "circlename": "Maharashtra",
    "Taluk": "Ratnagiri",
    "Districtname": "Ratnagiri",
    "statename": "MAHARASHTRA"
  }
]
