[
  {
    "pincode": "431122",
    "officename": "Beed H.O",
    "officeType": "H.O",
    "Deliverystatus": "Delivery",
    "divisionname": "Beed",
    "regionname": "Aurangabad",
    "circlename": "Maharashtra",
    "Taluk": "Beed",
    "Districtname": "Beed",
    "statename": "MAHARASHTRA"
  },
  {
    "pincode": "431122",
    "officename": "Court Road S.O",
    "officeType": "S.O",
    "Deliverystatus": "Non-Delivery",
    "divisionname": "Beed",
    "regionname": "Aurangabad",
    "circlename": "Maharashtra",
    "Taluk": "Bid",
    "Districtname": "Beed",
    "statename": "MAHARASHTRA"
  },
  {
    "pincode": "431122",
    "officename": "DHONDIPURA S.O",
    "officeType": "S.O",
    "Deliverystatus": "Non-Delivery",
    "divisionname": "Beed",
    "regionname": "Aurangabad",
    "circlename": "Maharashtra",
    "Taluk": "Bid",
    "Districtname": "Beed",
    "statename": "MAHARASHTRA"
  },
  {
    "pincode": "431122",
    "officename": "M.GANJ S.O",
    "officeType": "S.O",
    "Deliverystatus": "Non-Delivery",
    "divisionname": "Beed",
    "regionname": "Aurangabad",
    "circlename": "Maharashtra",
    "Taluk": "Bid",
    "Districtname": "Beed",
    "statename": "MAHARASHTRA"
  },
  {
    "pincode": "431122",
    "officename": "MARKET YARD S.O (Beed)",
    "officeType": "S.O",
    "Deliverystatus": "Non-Delivery",
    "divisionname": "Beed",
    "regionname": "Aurangabad",
    "circlename": "Maharashtra",
    "Taluk": "Bid",
    "Districtname": "Beed",
    "statename": "MAHARASHTRA"
  }
]
