[
  {
    "pincode": "471301",
    "officename": "Angore B.O",
    "officeType": "B.O",
    "Deliverystatus": "Delivery",
    "divisionname": "Chhatarpur",
    "regionname": "Bhopal HQ",
    "circlename": "Madhya Pradesh",
    "Taluk": "Malehara",
    "Districtname": "Chhatarpur",
    "statename": "MADHYA PRADESH"
  },
  {
    "pincode": "471301",
    "officename": "Atrar B.O",
    "officeType": "B.O",
    "Deliverystatus": "Delivery",
    "divisionname": "Chhatarpur",
    "regionname": "Bhopal HQ",
    "circlename": "Madhya Pradesh",
    "Taluk": "Malehara",
    "Districtname": "Chhatarpur",
    "statename": "MADHYA PRADESH"
  },
  {
    "pincode": "471301",
    "officename": "Bardwha B.O",
    "officeType": "B.O",
    "Deliverystatus": "Delivery",
    "divisionname": "Chhatarpur",
    "regionname": "Bhopal HQ",
    "circlename": "Madhya Pradesh",
    "Taluk": "Malehara",
    "Districtname": "Chhatarpur",
    "statename": "MADHYA PRADESH"
  },
  {
    "pincode": "471301",
    "officename": "Budore B.O",
    "officeType": "B.O",
    "Deliverystatus": "Delivery",
    "divisionname": "Chhatarpur",
    "regionname": "Bhopal HQ",
    "circlename": "Madhya Pradesh",
    "Taluk": "Malehara",
    "Districtname": "Chhatarpur",
    "statename": "MADHYA PRADESH"
  },
  {
    "pincode": "471301",
    "officename": "Chauka B.O",
    "officeType": "B.O",
    "Deliverystatus": "Delivery",
    "divisionname": "Chhatarpur",
    "regionname": "Bhopal HQ",
    "circlename": "Madhya Pradesh",
    "Taluk": "Malehara",
    "Districtname": "Chhatarpur",
    "statename": "MADHYA PRADESH"
  },
  {
    "pincode": "471301",
    "officename": "Dikoli B.O",
    "officeType": "B.O",
    "Deliverystatus": "Delivery",
    "divisionname": "Chhatarpur",
    "regionname": "Bhopal HQ",
    "circlename": "Madhya Pradesh",
    "Taluk": "Malehara",
    "Districtname": "Chhatarpur",
    "statename": "MADHYA PRADESH"
  },
  {
    "pincode": "471301",
    "officename": "Gulganj S.O",
    "officeType": "S.O",
    "Deliverystatus": "Delivery",
    "divisionname": "Chhatarpur",
    "regionname": "Bhopal HQ",
    "circlename": "Madhya Pradesh",
    "Taluk": "Malehra",
    "Districtname": "Chhatarpur",
    "statename": "MADHYA PRADESH"
  },
  {
    "pincode": "471301",
    "officename": "Kheron B.O",
    "officeType": "B.O",
    "Deliverystatus": "Delivery",
    "divisionname": "Chhatarpur",
    "regionname": "Bhopal HQ",
    "circlename": "Madhya Pradesh",
    "Taluk": "Malehara",
    "Districtname": "Chhatarpur",
    "statename": "MADHYA PRADESH"
  },
  {
    "pincode": "471301",
    "officename": "Matgawan B.O",
    "officeType": "B.O",
    "Deliverystatus": "Delivery",
    "divisionname": "Chhatarpur",
    "regionname": "Bhopal HQ",
    "circlename": "Madhya Pradesh",
    "Taluk": "Malehara",
    "Districtname": "Chhatarpur",
    "statename": "MADHYA PRADESH"
  }
]
