[
  {
    "pincode": "472337",
    "officename": "Bhopalpur B.O",
    "officeType": "B.O",
    "Deliverystatus": "Delivery",
    "divisionname": "Chhatarpur",
    "regionname": "Bhopal HQ",
    "circlename": "Madhya Pradesh",
    "Taluk": "Tikamgarh",
    "Districtname": "Tikamgarh",
    "statename": "MADHYA PRADESH"
  },
  {
    "pincode": "472337",
    "officename": "Birsagar B.O",
    "officeType": "B.O",
    "Deliverystatus": "Delivery",
    "divisionname": "Chhatarpur",
    "regionname": "Bhopal HQ",
    "circlename": "Madhya Pradesh",
    "Taluk": "Prithvipur",
    "Districtname": "Tikamgarh",
    "statename": "MADHYA PRADESH"
  },
  {
    "pincode": "472337",
    "officename": "Jerakhas B.O",
    "officeType": "B.O",
    "Deliverystatus": "Delivery",
    "divisionname": "Chhatarpur",
    "regionname": "Bhopal HQ",
    "circlename": "Madhya Pradesh",
    "Taluk": "Tikamgarh",
    "Districtname": "Tikamgarh",
    "statename": "MADHYA PRADESH"
  },
  {
    "pincode": "472337",
    "officename": "Jeron S.O",
    "officeType": "S.O",
    "Deliverystatus": "Delivery",
    "divisionname": "Chhatarpur",
    "regionname": "Bhopal HQ",
    "circlename": "Madhya Pradesh",
    "Taluk": "Prithvipur",
    "Districtname": "Tikamgarh",
    "statename": "MADHYA PRADESH"
  },
  {
    "pincode": "472337",
    "officename": "Kakwni B.O",
    "officeType": "B.O",
    "Deliverystatus": "Delivery",
    "divisionname": "Chhatarpur",
    "regionname": "Bhopal HQ",
    "circlename": "Madhya Pradesh",
    "Taluk": "Tikamgarh",
    "Districtname": "Tikamgarh",
    "statename": "MADHYA PRADESH"
  },
  {
    "pincode": "472337",
    "officename": "Loharguwn B.O",
    "officeType": "B.O",
    "Deliverystatus": "Delivery",
    "divisionname": "Chhatarpur",
    "regionname": "Bhopal HQ",
    "circlename": "Madhya Pradesh",
    "Taluk": "Tikamgarh",
    "Districtname": "Tikamgarh",
    "statename": "MADHYA PRADESH"
  },
  {
    "pincode": "472337",
    "officename": "Papawani B.O",
    "officeType": "B.O",
    "Deliverystatus": "Delivery",
    "divisionname": "Chhatarpur",
    "regionname": "Bhopal HQ",
    "circlename": "Madhya Pradesh",
    "Taluk": "Tikamgarh",
    "Districtname": "Tikamgarh",
    "statename": "MADHYA PRADESH"
  },
  {
    "pincode": "472337",
    "officename": "Simra B.O",
    "officeType": "B.O",
    "Deliverystatus": "Delivery",
    "divisionname": "Chhatarpur",
    "regionname": "Bhopal HQ",
    "circlename": "Madhya Pradesh",
    "Taluk": "Tikamgarh",
    "Districtname": "Tikamgarh",
    "statename": "MADHYA PRADESH"
  }
]
